intralinks/__init__.py
intralinks/api/__init__.py
intralinks/api/logger.py
intralinks/api/v1/__init__.py
intralinks/api/v2/__init__.py
intralinks/authenticators/__init__.py
intralinks/authenticators/v1/__init__.py
intralinks/authenticators/v1/authentication.py
intralinks/authenticators/v2/__init__.py
intralinks/authenticators/v2/authentication.py
intralinks/functions/__init__.py
intralinks/functions/entities.py
intralinks/functions/validations.py
intralinks/functions/v1/__init__.py
intralinks/functions/v1/alerts.py
intralinks/functions/v1/batches.py
intralinks/functions/v1/custom_alerts.py
intralinks/functions/v1/documents.py
intralinks/functions/v1/exchange_members.py
intralinks/functions/v1/exchanges.py
intralinks/functions/v1/fields.py
intralinks/functions/v1/folders.py
intralinks/functions/v1/groups.py
intralinks/functions/v1/permissions.py
intralinks/functions/v1/splashes.py
intralinks/functions/v1/user_accounts.py
intralinks/functions/v2/__init__.py
intralinks/functions/v2/alerts.py
intralinks/functions/v2/batches.py
intralinks/functions/v2/documents.py
intralinks/functions/v2/exchange_members.py
intralinks/functions/v2/exchanges.py
intralinks/functions/v2/fields.py
intralinks/functions/v2/folders.py
intralinks/functions/v2/groups.py
intralinks/functions/v2/permissions.py
intralinks/functions/v2/splashes.py
intralinks/functions/v2/user_accounts.py
intralinks/tools/__init__.py
intralinks/tools/custom_alert_manager.py
intralinks/tools/login_manager.py
intralinks/tools/notebooks_goodies.py
intralinks/tools/user_manager.py
intralinks/utils/__init__.py
intralinks/utils/associations.py
intralinks/utils/booleans.py
intralinks/utils/data.py
intralinks/utils/dates.py
intralinks/utils/files.py
intralinks/utils/http.py
intralinks/utils/test_data.py
intralinks/utils/xml.py
intralinks-0.1.6.dist-info/METADATA
intralinks-0.1.6.dist-info/RECORD
intralinks-0.1.6.dist-info/WHEEL
intralinks-0.1.6.dist-info/top_level.txt
intralinks_test/__init__.py
intralinks_test/conftest.py
intralinks_test/documents_helper.py
intralinks_test/documents_v1_test.py
