Metadata-Version: 2.1
Name: intralinks
Version: 0.1.6
Summary: A SDK for intralinks.com (for educational purpose only)
Home-page: https://github.com/ilapi/intralinks-api-python
Author: Olivier Mangez
Author-email: olivier.mangez@gmail.com
License: UNKNOWN
Platform: UNKNOWN
Classifier: Programming Language :: Python :: 3
Classifier: License :: OSI Approved :: MIT License
Classifier: Operating System :: OS Independent
Requires-Dist: requests (>0.23.4)
Requires-Dist: beautifulsoup4 (>4.4.0)
